flask_scarf/__init__.py
flask_scarf/cli/__init__.py
flask_scarf/cli/scarf.py
flask_scarf-0.2.data/scripts/scarf.py
flask_scarf-0.2.dist-info/DESCRIPTION.rst
flask_scarf-0.2.dist-info/METADATA
flask_scarf-0.2.dist-info/RECORD
flask_scarf-0.2.dist-info/WHEEL
flask_scarf-0.2.dist-info/metadata.json
flask_scarf-0.2.dist-info/top_level.txt
scarf/__init__.py
scarf/cli/__init__.py
scarf/cli/scarf.py
