Metadata-Version: 2.0
Name: flask-scarf
Version: 0.2
Summary: A battery included scafold generator for flask
Home-page: https://github.com/shuklaabhi/scarf
Author: Abhishek Shukla
Author-email: shukla.abhishek@outlook.com
License: BSD
Platform: any
Classifier: Development Status :: 1 - Planning
Classifier: Environment :: Console
Classifier: Framework :: Flask
Classifier: License :: OSI Approved :: BSD License
Classifier: Programming Language :: Python
Classifier: Programming Language :: Python :: 2.7
Classifier: Programming Language :: Python :: 3.4
Classifier: Programming Language :: Python :: 3.5
Classifier: Programming Language :: Python :: 3.6
Classifier: Programming Language :: Python :: Implementation :: CPython
Classifier: Programming Language :: Python :: Implementation :: PyPy
Classifier: Operating System :: OS Independent
